extract_mailchimp/__init__.py
extract_mailchimp/mail_chimp.py
extract_mailchimp-0.0.8.dist-info/LICENSE
extract_mailchimp-0.0.8.dist-info/METADATA
extract_mailchimp-0.0.8.dist-info/WHEEL
extract_mailchimp-0.0.8.dist-info/top_level.txt
extract_mailchimp-0.0.8.dist-info/RECORD
