Metadata-Version: 2.1
Name: extract-mailchimp
Version: 0.0.8
Summary: Extract MailChimp data only by folder ID
Author: Eunbin Park
Author-email: parkeb417@gmail.com
License: UNKNOWN
Keywords: data,api,mailchimp
Platform: UNKNOWN
Requires-Python: >=3.6
License-File: LICENSE
Requires-Dist: python-dotenv (==0.20.0)
Requires-Dist: mailchimp-marketing (>=3.0.75)
Requires-Dist: certifi (>=2017.4.17)
Requires-Dist: python-dateutil (>=2.1)
Requires-Dist: requests (>=2.23)
Requires-Dist: six (>=1.10)
Requires-Dist: urllib3 (>=1.23)
